{
    "name": "门",
    "type": "mesh",
    "geometry":[
    	{
            "id":"0",
    		"type":"boxGeometry",
    		"parameters":{"width":0.5,"height":15,"depth":8},
    		"rotation":{"x":0,"y":0,"z":0},
    		"translate":{"x":0,"y":0,"z":-4}
    	}
    ],
	"rotation":{"x":0,"y":0,"z":0},
	"translate":{"x":0,"y":7.5,"z":0},
    "scale":{"x":1,"y":1,"z":1},
	"material":{
        "type":"loadTexture",
        "url":"http://localhost:3000/lib/3D/mesh/door.png"
    },
    "alterId":0,
    "alternative":[
        {
            "rotation":{"x":0,"y":-1,"z":0},
            "translate":{"x":0,"y":0,"z":0}
        }
    ]
	
}